README.txt
setup.py
collective/__init__.py
collective.installedpackages.egg-info/PKG-INFO
collective.installedpackages.egg-info/SOURCES.txt
collective.installedpackages.egg-info/dependency_links.txt
collective.installedpackages.egg-info/entry_points.txt
collective.installedpackages.egg-info/namespace_packages.txt
collective.installedpackages.egg-info/not-zip-safe
collective.installedpackages.egg-info/requires.txt
collective.installedpackages.egg-info/top_level.txt
collective/installedpackages/README.txt
collective/installedpackages/__init__.py
collective/installedpackages/config.py
collective/installedpackages/configure.zcml
collective/installedpackages/testing.py
collective/installedpackages/browser/__init__.py
collective/installedpackages/browser/views.py
collective/installedpackages/browser/view_templates/installedpackagescontrolpanel.pt
collective/installedpackages/browser/view_templates/listpythonpackages.pt
collective/installedpackages/browser/view_templates/listsyspath.pt
collective/installedpackages/profiles/default/controlpanel.xml
collective/installedpackages/profiles/default/metadata.xml
collective/installedpackages/tests/__init__.py
collective/installedpackages/tests/test_views.py
docs/HISTORY.txt