Metadata-Version: 1.0
Name: collective.installedpackages
Version: 0.1b2
Summary: Add-on for Plone to list all Python packages available to the running Python process, its versionsand other information about them.
Home-page: http://svn.plone.org/svn/collective/collective.installedpackages
Author: Rafael Oliveira
Author-email: rafaelbco@gmail.com
License: GPL
Keywords: plone dexterity
Platform: UNKNOWN
Classifier: Programming Language :: Python
Classifier: Framework :: Plone
